[
  {
    "type": "created",
    "timestamp": "2025-01-16T08:37:45Z",
    "actor": "franvila"
  },
  {
    "type": "review_requested",
    "timestamp": "2025-01-16T08:37:45Z",
    "actor": "franvila"
  },
  {
    "type": "review_requested",
    "timestamp": "2025-01-16T08:37:45Z",
    "actor": "franvila"
  },
  {
    "type": "comment",
    "timestamp": "2025-01-16T08:37:58Z",
    "actor": "franvila"
  },
  {
    "type": "comment",
    "timestamp": "2025-01-16T08:47:13Z",
    "actor": "strimzi-ci"
  },
  {
    "type": "comment",
    "timestamp": "2025-01-16T09:22:39Z",
    "actor": "strimzi-ci"
  },
  {
    "type": "reviewed",
    "timestamp": "2025-01-16T23:15:25Z",
    "actor": "k-wall"
  },
  {
    "type": "comment",
    "timestamp": "2025-01-17T07:09:50Z",
    "actor": "sonarqubecloud[bot]"
  },
  {
    "type": "closed_merged",
    "timestamp": "2025-01-17T07:09:51Z",
    "actor": null
  }
]
