[
  {
    "type": "created",
    "timestamp": "2026-03-30T03:35:03Z",
    "actor": "dependabot[bot]"
  },
  {
    "type": "review_requested",
    "timestamp": "2026-03-30T03:35:04Z",
    "actor": "dependabot[bot]"
  },
  {
    "type": "reviewed",
    "timestamp": "2026-04-03T14:52:22Z",
    "actor": "k-wall"
  },
  {
    "type": "reviewed",
    "timestamp": "2026-04-03T14:54:49Z",
    "actor": "k-wall"
  },
  {
    "type": "comment",
    "timestamp": "2026-04-03T15:19:15Z",
    "actor": "sonarqubecloud[bot]"
  },
  {
    "type": "comment",
    "timestamp": "2026-04-03T15:20:52Z",
    "actor": "sonarqubecloud[bot]"
  },
  {
    "type": "closed_merged",
    "timestamp": "2026-04-03T15:20:53Z",
    "actor": null
  }
]
