[
  {
    "type": "created",
    "timestamp": "2026-01-05T23:06:13Z",
    "actor": "robobario"
  },
  {
    "type": "review_requested",
    "timestamp": "2026-01-05T23:06:14Z",
    "actor": "robobario"
  },
  {
    "type": "comment",
    "timestamp": "2026-01-06T01:05:59Z",
    "actor": "robobario"
  },
  {
    "type": "reviewed",
    "timestamp": "2026-01-06T20:17:29Z",
    "actor": "robobario"
  },
  {
    "type": "reviewed",
    "timestamp": "2026-01-07T22:00:19Z",
    "actor": "tombentley"
  },
  {
    "type": "comment",
    "timestamp": "2026-01-07T22:15:16Z",
    "actor": "robobario"
  },
  {
    "type": "comment",
    "timestamp": "2026-01-08T22:05:32Z",
    "actor": "sonarqubecloud[bot]"
  },
  {
    "type": "comment",
    "timestamp": "2026-01-12T02:30:48Z",
    "actor": "robobario"
  },
  {
    "type": "closed_unmerged",
    "timestamp": "2026-01-12T02:31:00Z",
    "actor": null
  }
]
