[
  {
    "type": "created",
    "timestamp": "2026-06-30T20:52:53Z",
    "actor": "robobario"
  },
  {
    "type": "review_requested",
    "timestamp": "2026-06-30T20:52:54Z",
    "actor": "robobario"
  },
  {
    "type": "reviewed",
    "timestamp": "2026-06-30T21:03:24Z",
    "actor": "robobario",
    "author_association": "MEMBER"
  },
  {
    "type": "reviewed",
    "timestamp": "2026-06-30T21:55:48Z",
    "actor": "SamBarker",
    "author_association": "MEMBER"
  },
  {
    "type": "comment",
    "timestamp": "2026-06-30T23:12:30Z",
    "actor": "sonarqubecloud[bot]",
    "author_association": "NONE"
  },
  {
    "type": "comment",
    "timestamp": "2026-06-30T23:14:08Z",
    "actor": "sonarqubecloud[bot]",
    "author_association": "NONE"
  },
  {
    "type": "closed_merged",
    "timestamp": "2026-06-30T23:14:09Z",
    "actor": null
  }
]
