[
  {
    "type": "created",
    "timestamp": "2026-06-02T01:53:01Z",
    "actor": "robobario"
  },
  {
    "type": "review_requested",
    "timestamp": "2026-06-02T01:53:02Z",
    "actor": "robobario"
  },
  {
    "type": "reviewed",
    "timestamp": "2026-06-02T09:29:04Z",
    "actor": "k-wall"
  },
  {
    "type": "comment",
    "timestamp": "2026-06-02T22:08:32Z",
    "actor": "sonarqubecloud[bot]"
  },
  {
    "type": "comment",
    "timestamp": "2026-06-02T22:09:54Z",
    "actor": "sonarqubecloud[bot]"
  },
  {
    "type": "reviewed",
    "timestamp": "2026-06-02T22:11:22Z",
    "actor": "SamBarker"
  },
  {
    "type": "closed_merged",
    "timestamp": "2026-06-02T22:27:58Z",
    "actor": null
  }
]
