[
  {
    "type": "created",
    "timestamp": "2026-05-06T05:22:45Z",
    "actor": "tombentley"
  },
  {
    "type": "review_requested",
    "timestamp": "2026-05-06T05:22:46Z",
    "actor": "tombentley"
  },
  {
    "type": "review_requested",
    "timestamp": "2026-05-06T05:22:54Z",
    "actor": "tombentley"
  },
  {
    "type": "reviewed",
    "timestamp": "2026-05-10T20:54:58Z",
    "actor": "robobario",
    "author_association": "MEMBER"
  },
  {
    "type": "comment",
    "timestamp": "2026-05-10T21:20:01Z",
    "actor": "sonarqubecloud[bot]",
    "author_association": "NONE"
  },
  {
    "type": "comment",
    "timestamp": "2026-05-10T21:21:21Z",
    "actor": "sonarqubecloud[bot]",
    "author_association": "NONE"
  },
  {
    "type": "closed_merged",
    "timestamp": "2026-05-10T21:21:34Z",
    "actor": null
  }
]
