[
  {
    "type": "created",
    "timestamp": "2026-04-24T01:23:09Z",
    "actor": "kroxylicious-robot"
  },
  {
    "type": "review_requested",
    "timestamp": "2026-04-24T01:23:10Z",
    "actor": "kroxylicious-robot"
  },
  {
    "type": "reviewed",
    "timestamp": "2026-04-24T15:23:21Z",
    "actor": "k-wall"
  },
  {
    "type": "comment",
    "timestamp": "2026-04-25T07:53:47Z",
    "actor": "sonarqubecloud[bot]"
  },
  {
    "type": "comment",
    "timestamp": "2026-04-25T07:55:04Z",
    "actor": "sonarqubecloud[bot]"
  },
  {
    "type": "closed_merged",
    "timestamp": "2026-04-25T07:55:39Z",
    "actor": null
  }
]
