[
  {
    "type": "created",
    "timestamp": "2026-02-16T03:37:31Z",
    "actor": "dependabot[bot]"
  },
  {
    "type": "review_requested",
    "timestamp": "2026-02-16T03:37:32Z",
    "actor": "dependabot[bot]"
  },
  {
    "type": "comment",
    "timestamp": "2026-02-16T04:25:58Z",
    "actor": "sonarqubecloud[bot]"
  },
  {
    "type": "comment",
    "timestamp": "2026-02-16T04:27:17Z",
    "actor": "sonarqubecloud[bot]"
  },
  {
    "type": "reviewed",
    "timestamp": "2026-02-16T06:01:22Z",
    "actor": "franvila"
  },
  {
    "type": "closed_merged",
    "timestamp": "2026-02-16T06:01:28Z",
    "actor": null
  }
]
