[
  {
    "type": "created",
    "timestamp": "2026-07-01T03:47:31Z",
    "actor": "SamBarker"
  },
  {
    "type": "review_requested",
    "timestamp": "2026-07-03T00:20:26Z",
    "actor": "SamBarker"
  },
  {
    "type": "reviewed",
    "timestamp": "2026-07-03T04:38:28Z",
    "actor": "robobario",
    "author_association": "MEMBER"
  },
  {
    "type": "comment",
    "timestamp": "2026-07-03T07:01:03Z",
    "actor": "sonarqubecloud[bot]",
    "author_association": "NONE"
  },
  {
    "type": "comment",
    "timestamp": "2026-07-03T07:02:53Z",
    "actor": "sonarqubecloud[bot]",
    "author_association": "NONE"
  },
  {
    "type": "closed_merged",
    "timestamp": "2026-07-03T07:02:54Z",
    "actor": null
  }
]
