[
  {
    "type": "created",
    "timestamp": "2025-08-25T09:31:17Z",
    "actor": "dependabot[bot]"
  },
  {
    "type": "review_requested",
    "timestamp": "2025-08-25T09:31:18Z",
    "actor": "dependabot[bot]"
  },
  {
    "type": "comment",
    "timestamp": "2025-08-25T23:21:58Z",
    "actor": "robobario"
  },
  {
    "type": "comment",
    "timestamp": "2025-08-26T00:16:19Z",
    "actor": "sonarqubecloud[bot]"
  },
  {
    "type": "reviewed",
    "timestamp": "2025-09-11T17:50:01Z",
    "actor": "k-wall"
  },
  {
    "type": "closed_merged",
    "timestamp": "2025-09-11T17:50:12Z",
    "actor": null
  }
]
