[
  {
    "type": "created",
    "timestamp": "2023-11-20T05:21:53Z",
    "actor": "dependabot[bot]"
  },
  {
    "type": "comment",
    "timestamp": "2023-11-20T05:22:17Z",
    "actor": "sonarqubecloud[bot]"
  },
  {
    "type": "comment",
    "timestamp": "2023-11-20T11:30:59Z",
    "actor": "k-wall"
  },
  {
    "type": "comment",
    "timestamp": "2023-11-20T11:31:02Z",
    "actor": "dependabot[bot]"
  },
  {
    "type": "closed_unmerged",
    "timestamp": "2023-11-20T11:31:03Z",
    "actor": null
  }
]
