[
  {
    "type": "created",
    "timestamp": "2026-07-07T11:22:04Z",
    "actor": "k-wall"
  },
  {
    "type": "review_requested",
    "timestamp": "2026-07-07T11:22:05Z",
    "actor": "k-wall"
  },
  {
    "type": "comment",
    "timestamp": "2026-07-07T11:25:55Z",
    "actor": "k-wall"
  },
  {
    "type": "comment",
    "timestamp": "2026-07-07T13:22:25Z",
    "actor": "k-wall"
  },
  {
    "type": "reviewed",
    "timestamp": "2026-07-08T03:17:07Z",
    "actor": "SamBarker"
  },
  {
    "type": "comment",
    "timestamp": "2026-07-08T03:48:12Z",
    "actor": "sonarqubecloud[bot]"
  },
  {
    "type": "comment",
    "timestamp": "2026-07-08T03:49:56Z",
    "actor": "sonarqubecloud[bot]"
  },
  {
    "type": "closed_merged",
    "timestamp": "2026-07-08T03:49:57Z",
    "actor": null
  }
]
