[
  {
    "type": "created",
    "timestamp": "2025-04-21T04:02:19Z",
    "actor": "dependabot[bot]"
  },
  {
    "type": "review_requested",
    "timestamp": "2025-04-21T04:02:20Z",
    "actor": "dependabot[bot]"
  },
  {
    "type": "reviewed",
    "timestamp": "2025-04-22T03:28:29Z",
    "actor": "SamBarker"
  },
  {
    "type": "comment",
    "timestamp": "2025-04-22T03:28:32Z",
    "actor": "dependabot[bot]"
  },
  {
    "type": "comment",
    "timestamp": "2025-04-22T03:55:30Z",
    "actor": "sonarqubecloud[bot]"
  },
  {
    "type": "closed_merged",
    "timestamp": "2025-04-22T03:56:56Z",
    "actor": null
  }
]
