[
  {
    "type": "created",
    "timestamp": "2026-01-09T09:17:41Z",
    "actor": "kroxylicious-robot"
  },
  {
    "type": "review_requested",
    "timestamp": "2026-01-09T09:17:42Z",
    "actor": "kroxylicious-robot"
  },
  {
    "type": "comment",
    "timestamp": "2026-01-11T22:56:46Z",
    "actor": "robobario"
  },
  {
    "type": "comment",
    "timestamp": "2026-01-11T22:57:41Z",
    "actor": "kroxylicious-robot"
  },
  {
    "type": "comment",
    "timestamp": "2026-01-12T00:18:33Z",
    "actor": "kroxylicious-robot"
  },
  {
    "type": "reviewed",
    "timestamp": "2026-01-12T01:19:13Z",
    "actor": "robobario"
  },
  {
    "type": "comment",
    "timestamp": "2026-01-12T01:38:22Z",
    "actor": "sonarqubecloud[bot]"
  },
  {
    "type": "closed_merged",
    "timestamp": "2026-01-12T01:39:43Z",
    "actor": null
  }
]
