[
  {
    "type": "created",
    "timestamp": "2024-04-22T03:39:55Z",
    "actor": "dependabot[bot]"
  },
  {
    "type": "comment",
    "timestamp": "2024-04-22T04:22:01Z",
    "actor": "sonarqubecloud[bot]"
  },
  {
    "type": "comment",
    "timestamp": "2024-04-22T04:39:22Z",
    "actor": "robobario"
  },
  {
    "type": "comment",
    "timestamp": "2024-04-22T04:39:25Z",
    "actor": "dependabot[bot]"
  },
  {
    "type": "reviewed",
    "timestamp": "2024-04-22T04:39:33Z",
    "actor": "robobario"
  },
  {
    "type": "comment",
    "timestamp": "2024-04-22T04:39:44Z",
    "actor": "robobario"
  },
  {
    "type": "closed_merged",
    "timestamp": "2024-04-22T04:39:47Z",
    "actor": null
  }
]
