[
  {
    "type": "created",
    "timestamp": "2025-12-10T22:54:39Z",
    "actor": "robobario"
  },
  {
    "type": "review_requested",
    "timestamp": "2025-12-10T22:54:40Z",
    "actor": "robobario"
  },
  {
    "type": "comment",
    "timestamp": "2025-12-10T23:15:17Z",
    "actor": "robobario"
  },
  {
    "type": "comment",
    "timestamp": "2025-12-10T23:17:48Z",
    "actor": "robobario"
  },
  {
    "type": "comment",
    "timestamp": "2025-12-11T00:27:11Z",
    "actor": "robobario"
  },
  {
    "type": "comment",
    "timestamp": "2025-12-11T00:56:44Z",
    "actor": "robobario"
  },
  {
    "type": "reviewed",
    "timestamp": "2025-12-11T19:23:01Z",
    "actor": "k-wall"
  },
  {
    "type": "reviewed",
    "timestamp": "2025-12-11T19:25:17Z",
    "actor": "k-wall"
  },
  {
    "type": "comment",
    "timestamp": "2025-12-11T23:12:58Z",
    "actor": "sonarqubecloud[bot]"
  },
  {
    "type": "closed_merged",
    "timestamp": "2025-12-11T23:12:59Z",
    "actor": null
  }
]
